love_rimi/__init__.py
love_rimi/manage.py
love_rimi/this.py
love_rimi/this_un/__init__.py
love_rimi/this_un/check.py
love_rimi/this_un/crypto.py
love_rimi/this_un/this_un.py
love_rimi/this_un/lang/ar.lang
love_rimi/this_un/lang/de.lang
love_rimi/this_un/lang/fr.lang
love_rimi/this_un/lang/zh_chs.lang
love_rimi/this_un/lang/zh_cht.lang
love_rimi-0.0.1.3.dist-info/LICENSE
love_rimi-0.0.1.3.dist-info/METADATA
love_rimi-0.0.1.3.dist-info/WHEEL
love_rimi-0.0.1.3.dist-info/entry_points.txt
love_rimi-0.0.1.3.dist-info/top_level.txt
love_rimi-0.0.1.3.dist-info/RECORD
