Metadata-Version: 2.1
Name: love_rimi
Version: 0.0.1.3
Summary: A package used to describe love between Rimi and Sandmeyer
Home-page: https://github.com/SandmX/love_rimi
Author: Sandmeyer
Author-email: sandmx.work@gmail.com
Classifier: Programming Language :: Python :: 3
Classifier: License :: OSI Approved :: GNU General Public License v3 or later (GPLv3+)
Classifier: Operating System :: OS Independent
Requires-Python: >=3.6
License-File: LICENSE
Requires-Dist: rich>=13.7.1
Requires-Dist: setuptools==72.2.0
